{
	"meta": {
		"image": "spritesheet.png",
		"size": {"w":483,"h":409},
		"scale": "1"
	},
	"frames": {
		"Logo1A_V1.png":
		{
			"frame": {"x":0,"y":0,"w":173,"h":174},
			"rotated": false,
			"trimmed": true,
			"spriteSourceSize": {"x":8,"y":7,"w":173,"h":174},
			"sourceSize": {"w":188,"h":188}
		},
		"AI_Entity_Opt6.png":
		{
			"frame": {"x":173,"y":0,"w":80,"h":80},
			"rotated": false,
			"trimmed": false,
			"spriteSourceSize": {"x":0,"y":0,"w":80,"h":80},
			"sourceSize": {"w":80,"h":80}
		},
		"AI_Entity_Opt6A_Powerup.png":
		{
			"frame": {"x":173,"y":80,"w":80,"h":80},
			"rotated": false,
			"trimmed": false,
			"spriteSourceSize": {"x":0,"y":0,"w":80,"h":80},
			"sourceSize": {"w":80,"h":80}
		},
		"AI_Entity_Opt7.png":
		{
			"frame": {"x":253,"y":0,"w":80,"h":80},
			"rotated": false,
			"trimmed": false,
			"spriteSourceSize": {"x":0,"y":0,"w":80,"h":80},
			"sourceSize": {"w":80,"h":80}
		},
		"AI_Entity_Opt7A_Powerup.png":
		{
			"frame": {"x":253,"y":80,"w":80,"h":80},
			"rotated": false,
			"trimmed": false,
			"spriteSourceSize": {"x":0,"y":0,"w":80,"h":80},
			"sourceSize": {"w":80,"h":80}
		},
		"Battle_Token_Opt1.png":
		{
			"frame": {"x":0,"y":174,"w":80,"h":80},
			"rotated": false,
			"trimmed": false,
			"spriteSourceSize": {"x":0,"y":0,"w":80,"h":80},
			"sourceSize": {"w":80,"h":80}
		},
		"Battle_Token_Opt2.png":
		{
			"frame": {"x":80,"y":174,"w":80,"h":80},
			"rotated": false,
			"trimmed": false,
			"spriteSourceSize": {"x":0,"y":0,"w":80,"h":80},
			"sourceSize": {"w":80,"h":80}
		},
		"Battle_Token_Opt3.png":
		{
			"frame": {"x":160,"y":174,"w":80,"h":80},
			"rotated": false,
			"trimmed": false,
			"spriteSourceSize": {"x":0,"y":0,"w":80,"h":80},
			"sourceSize": {"w":80,"h":80}
		},
		"PowerUp_token_Opt2.png":
		{
			"frame": {"x":240,"y":174,"w":80,"h":80},
			"rotated": false,
			"trimmed": false,
			"spriteSourceSize": {"x":0,"y":0,"w":80,"h":80},
			"sourceSize": {"w":80,"h":80}
		},
		"Power_Source_Opt3.png":
		{
			"frame": {"x":333,"y":0,"w":80,"h":80},
			"rotated": false,
			"trimmed": false,
			"spriteSourceSize": {"x":0,"y":0,"w":80,"h":80},
			"sourceSize": {"w":80,"h":80}
		},
		"Power_Source_Opt4.png":
		{
			"frame": {"x":333,"y":80,"w":80,"h":80},
			"rotated": false,
			"trimmed": false,
			"spriteSourceSize": {"x":0,"y":0,"w":80,"h":80},
			"sourceSize": {"w":80,"h":80}
		},
		"SolarS_Opt1.png":
		{
			"frame": {"x":333,"y":160,"w":80,"h":80},
			"rotated": false,
			"trimmed": false,
			"spriteSourceSize": {"x":0,"y":0,"w":80,"h":80},
			"sourceSize": {"w":80,"h":80}
		},
		"SolarS_Opt3.png":
		{
			"frame": {"x":0,"y":254,"w":80,"h":80},
			"rotated": false,
			"trimmed": false,
			"spriteSourceSize": {"x":0,"y":0,"w":80,"h":80},
			"sourceSize": {"w":80,"h":80}
		},
		"Wormhole_Opt2.png":
		{
			"frame": {"x":80,"y":254,"w":80,"h":80},
			"rotated": false,
			"trimmed": false,
			"spriteSourceSize": {"x":0,"y":0,"w":80,"h":80},
			"sourceSize": {"w":80,"h":80}
		},
		"Wormhole_Opt3.png":
		{
			"frame": {"x":160,"y":254,"w":80,"h":80},
			"rotated": false,
			"trimmed": false,
			"spriteSourceSize": {"x":0,"y":0,"w":80,"h":80},
			"sourceSize": {"w":80,"h":80}
		},
		"PowerUp_token_Opt1.png":
		{
			"frame": {"x":240,"y":254,"w":78,"h":80},
			"rotated": false,
			"trimmed": true,
			"spriteSourceSize": {"x":2,"y":0,"w":78,"h":80},
			"sourceSize": {"w":80,"h":80}
		},
		"Wormhole_Opt1.png":
		{
			"frame": {"x":318,"y":254,"w":78,"h":80},
			"rotated": false,
			"trimmed": true,
			"spriteSourceSize": {"x":0,"y":0,"w":78,"h":80},
			"sourceSize": {"w":80,"h":80}
		},
		"Power_Source_Opt2.png":
		{
			"frame": {"x":0,"y":334,"w":80,"h":75},
			"rotated": false,
			"trimmed": false,
			"spriteSourceSize": {"x":0,"y":0,"w":80,"h":75},
			"sourceSize": {"w":80,"h":75}
		},
		"AI_Entity_Opt4.png":
		{
			"frame": {"x":413,"y":0,"w":70,"h":80},
			"rotated": false,
			"trimmed": false,
			"spriteSourceSize": {"x":0,"y":0,"w":70,"h":80},
			"sourceSize": {"w":70,"h":80}
		},
		"AI_Entity_Opt4A_Powerup.png":
		{
			"frame": {"x":413,"y":80,"w":70,"h":80},
			"rotated": false,
			"trimmed": false,
			"spriteSourceSize": {"x":0,"y":0,"w":70,"h":80},
			"sourceSize": {"w":70,"h":80}
		},
		"AI_Entity_Opt5.png":
		{
			"frame": {"x":413,"y":160,"w":70,"h":80},
			"rotated": false,
			"trimmed": false,
			"spriteSourceSize": {"x":0,"y":0,"w":70,"h":80},
			"sourceSize": {"w":70,"h":80}
		},
		"AI_Entity_Opt5A_Powerup.png":
		{
			"frame": {"x":413,"y":240,"w":70,"h":80},
			"rotated": false,
			"trimmed": false,
			"spriteSourceSize": {"x":0,"y":0,"w":70,"h":80},
			"sourceSize": {"w":70,"h":80}
		},
		"Power_Source_Opt1.png":
		{
			"frame": {"x":80,"y":334,"w":76,"h":75},
			"rotated": false,
			"trimmed": true,
			"spriteSourceSize": {"x":0,"y":0,"w":76,"h":75},
			"sourceSize": {"w":80,"h":75}
		}
	}
}